<marklogic><id>tag:search.twitter.com,2005:182984343101247489</id><type>P</type><type>P</type><body>Always wanted to try out a Cold shower.. Too shook though :|</body><verb>post</verb><link>http://twitter.com/RC_Mahachi/statuses/182984343101247489</link><generator><link>http://ubersocial.com</link><displayName>UberSocial for BlackBerry</displayName></generator><postedTime>2012-03-23T00:17:21.000Z</postedTime><provider><link>http://www.twitter.com</link><displayName>Twitter</displayName><objectType>service</objectType></provider><object><summary>Always wanted to try out a cold shower.. Too shook though :|</summary><id>object:search.twitter.com,2005:182984343101247489</id><link>http://twitter.com/RC_Mahachi/statuses/182984343101247489</link><postedTime>2012-03-23T00:17:21.000Z</postedTime><objectType>note</objectType></object><actor><summary>† LiveLifeLove| The future belongs to those who prepare today.. </summary><twitterTimeZone>London</twitterTimeZone><friendsCount>97</friendsCount><location><displayName>Northampton, UK</displayName><objectType>place</objectType></location><link>http://www.twitter.com/RC_Mahachi</link><postedTime>2011-12-20T18:49:37.000Z</postedTime><image>http://a0.twimg.com/profile_images/1923065385/336460381_normal.jpg</image><links><links><rel>me</rel><href/></links></links><listedCount>0</listedCount><id>id:twitter.com:442086068</id><languages><languages>en</languages></languages><utcOffset>0</utcOffset><followersCount>77</followersCount><preferredUsername>RC_Mahachi</preferredUsername><displayName>Clinton Mahachi</displayName><statusesCount>725</statusesCount><objectType>person</objectType></actor><twitter_entities><urls/><user_mentions/><hashtags/></twitter_entities><objectType>activity</objectType><platform>twitter</platform><posted_date>2012-03-23</posted_date><followers>77</followers><statuses>725</statuses><region>London</region></marklogic>