<marklogic><id>tag:search.twitter.com,2005:184318979286908929</id><type>P</type><type>P</type><inReplyTo><link>http://twitter.com/kidblaque33/statuses/184318484946235393</link></inReplyTo><body>@kidblaque33 Thanks for checking in! Soothe your allergy-related Cough and Sore throat with HALLS Cough drops: http://t.co/7dKocNBu</body><verb>post</verb><link>http://twitter.com/Walgreens/statuses/184318979286908929</link><generator><link>http://localresponse.com</link><displayName>LocalResponse for Walgreens</displayName></generator><postedTime>2012-03-26T16:40:43.000Z</postedTime><provider><link>http://www.twitter.com</link><displayName>Twitter</displayName><objectType>service</objectType></provider><object><summary>@kidblaque33 Thanks for checking in! Soothe your allergy-related cough and sore throat with HALLS cough drops: http://t.co/7dKocNBu</summary><id>object:search.twitter.com,2005:184318979286908929</id><link>http://twitter.com/Walgreens/statuses/184318979286908929</link><postedTime>2012-03-26T16:40:43.000Z</postedTime><objectType>note</objectType></object><actor><summary>Walgreens is the nation’s largest drugstore chain with more than 7,500 drugstores in all 50 states, the District of Columbia and Puerto Rico.</summary><twitterTimeZone>Central Time (US &amp; Canada)</twitterTimeZone><friendsCount>2382</friendsCount><location><displayName>Chicago, IL</displayName><objectType>place</objectType></location><link>http://www.twitter.com/Walgreens</link><postedTime>2009-06-10T17:56:29.000Z</postedTime><image>http://a0.twimg.com/profile_images/1565658805/Wag_W_Red_normal.png</image><links><links><rel>me</rel><href>http://www.walgreens.com</href></links></links><listedCount>1280</listedCount><id>id:twitter.com:46177695</id><languages><languages>en</languages></languages><utcOffset>-21600</utcOffset><followersCount>90646</followersCount><preferredUsername>Walgreens</preferredUsername><displayName>Walgreens</displayName><statusesCount>14439</statusesCount><objectType>person</objectType></actor><twitter_entities><urls><urls><expanded_url>http://bz.lo.cr/P5d</expanded_url><indices><indices>111</indices><indices>131</indices></indices><display_url>bz.lo.cr/P5d</display_url><url>http://t.co/7dKocNBu</url></urls></urls><hashtags/><user_mentions><user_mentions><id_str>302427972</id_str><indices><indices>0</indices><indices>12</indices></indices><name>Rob White</name><screen_name>kidblaque33</screen_name><id>302427972</id></user_mentions></user_mentions></twitter_entities><objectType>activity</objectType><platform>twitter</platform><posted_date>2012-03-26</posted_date><followers>90646</followers><statuses>14439</statuses><region>Central</region></marklogic>