<marklogic><id>tag:search.twitter.com,2005:182934587071139842</id><type>P</type><type>P</type><body>This Headache has put me in a bad mood. I just want a Ribena &amp;amp; lots of cuddles from....... Lol *Sigh*</body><verb>post</verb><link>http://twitter.com/MissReeBby/statuses/182934587071139842</link><generator><link>http://www.echofon.com/</link><displayName>Echofon</displayName></generator><postedTime>2012-03-22T20:59:38.000Z</postedTime><provider><link>http://www.twitter.com</link><displayName>Twitter</displayName><objectType>service</objectType></provider><object><summary>This headache has put me in a bad mood. I just want a Ribena &amp;amp; lots of cuddles from....... Lol *Sigh*</summary><id>object:search.twitter.com,2005:182934587071139842</id><link>http://twitter.com/MissReeBby/statuses/182934587071139842</link><postedTime>2012-03-22T20:59:38.000Z</postedTime><objectType>note</objectType></object><actor><summary>God, Ribena &amp; Happiness... We bout that life! âœŒâ&#157;¤â&#157;¤â&#157;¤</summary><twitterTimeZone>London</twitterTimeZone><friendsCount>232</friendsCount><link>http://www.twitter.com/MissReeBby</link><postedTime>2009-12-03T15:57:36.000Z</postedTime><image>http://a0.twimg.com/profile_images/1909031037/MissReeBby_normal.jpg</image><links><links><rel>me</rel><href/></links></links><listedCount>19</listedCount><id>id:twitter.com:94356195</id><languages><languages>en</languages></languages><utcOffset>0</utcOffset><followersCount>663</followersCount><preferredUsername>MissReeBby</preferredUsername><displayName>R.B î€‘</displayName><statusesCount>44078</statusesCount><objectType>person</objectType></actor><twitter_entities><urls/><user_mentions/><hashtags/></twitter_entities><objectType>activity</objectType><platform>twitter</platform><posted_date>2012-03-22</posted_date><followers>663</followers><statuses>44078</statuses><region>London</region></marklogic>