<marklogic><id>tag:gnip.disqus.com:2012:comment/mkq4r6/update/2012-03-26T01:54:30/80ae9edf7ad225adb721aeac503e2d1fd2d8e16030705441c9d50097dcda5549</id><type>P</type><type>P</type><body>This is getting a bit silly. The first incident I could still believe, but this last one I would say is someone jumping on the band wagon hoping to get something out of it. Firstly when someone is working out, chances that there spit would be a Cold liquid is highly unlikely. I would say this was one of those steroid monkeys lifting half a car. Those guys often spit, growl and drop weights indiscriminately. I don't agree with it but I wont go calling it a racist attack. I have never been at a VA where there is a divide between black and white, I Always found it quite socially mixed. </body><verb>update</verb><target><id>tag:gnip.disqus.com:2012:thread/6r1a3n</id><website><id>tag:gnip.disqus.com:2012:forum/4uu5</id></website><link>http://news.iafrica.com/sa/786059.html</link><postedTime>2012-03-26T04:43:15+00:00</postedTime><objectType>article</objectType></target><postedTime>2012-03-26T05:54:30+00:00</postedTime><object><id>tag:gnip.disqus.com:2012:comment/mkq4r6</id><link>http://news.iafrica.com/sa/786059.html#comment-476241526</link><objectType>comment</objectType></object><actor><id>tag:gnip.disqus.com:2012:account/hrzfk</id><objectType>person</objectType></actor><disqusTypePrev>approved</disqusTypePrev><disqusType>approved</disqusType><platform>disqus</platform><posted_date>2012-03-26</posted_date><followers>0</followers><statuses>0</statuses><region>N.A.</region></marklogic>