<marklogic><id>tag:gnip.intensedebate.com:2012:blog/319394/post/127553463/comment/327609434</id><type>P</type><type>P</type><body>I don&amp;#039;t recall that far back but when the doctor first put me on Ambien I was wowed! My husband falls asleep within seconds of getting in bed. I had NEVER had a similar experience. Ambien showed me that it was possible to get in bed and go to sleep. I gave up on trying to quit taking it. I&amp;#039;ll cut back in other ways. I need my sleep! 
 
On the soda .... I&amp;#039;m still good! I would like a Coke Zero but I wouldn&amp;#039;t stop at one! I&amp;#039;m drinking water. Lots and lots of water! And the Headache is gone. So ... Sunday I will be putting the kabosh on sugar! Wish me well! 
My recent post &lt;a href="http:\/\/www.bethszimmerman.com\/2012\/03\/29\/easter-basket\/" target="_blank"&gt;Easter Basket&lt;/a&gt; </body><verb>post</verb><target><id>article:intensedebate.com:319394:127553463</id><idPostId>127553463</idPostId><idBlogId>319394</idBlogId><idBlog><id>blog:intensedebate.com:319394</id><idBlogId>319394</idBlogId><link>http://www.bethszimmerman.com</link><displayName>Beth: A Work in Progress</displayName><objectType>blog</objectType></idBlog><link>http://www.bethszimmerman.com/2012/03/27/and-then-i-tripped-over-the-cat/</link><displayName>And Then I Tripped Over the Cat</displayName><objectType>article</objectType></target><postedTime>2012-03-30T05:46:12.000Z</postedTime><provider><link>http://im.wordpress.com:8008/comments.json</link><displayName>IntenseDebate</displayName><objectType>service</objectType></provider><object><id>comment:intensedebate.com:319394:127553463:327609434</id><inReplyTo><link>http://www.bethszimmerman.com/2012/03/27/and-then-i-tripped-over-the-cat/#IDComment326410383</link></inReplyTo><link>http://www.bethszimmerman.com/2012/03/27/and-then-i-tripped-over-the-cat/#IDComment327609434</link><postedTime>2012-03-30T05:46:12.000Z</postedTime><displayName>Comment on And Then I Tripped Over the Cat by Beth Zimmerman</displayName><objectType>comment</objectType></object><actor><link>http://intensedebate.com/profiles/bethzimmerman</link><idEmailMd5>e33be9b973126a009847abc22833ee9b</idEmailMd5><displayName>Beth Zimmerman</displayName><objectType>person</objectType></actor><displayName>&lt;a href="http://intensedebate.com/profiles/bethzimmerman"&gt;Beth Zimmerman&lt;/a&gt; commented on &lt;a href="http://www.bethszimmerman.com/2012/03/27/and-then-i-tripped-over-the-cat/"&gt;And Then I Tripped Over the Cat&lt;/a&gt;</displayName><platform>intense-debate</platform><posted_date>2012-03-30</posted_date><followers>0</followers><statuses>0</statuses><region>N.A.</region></marklogic>