<marklogic><id>tag:gnip.disqus.com:2012:comment/mwm0kc/update/2012-03-30T09:33:51/615c8cf951842e31ad1313c7ac1ff839d30a394e914e4b2f1c0a93642b6dc793</id><type>P</type><type>P</type><body>You are all wrong, Tevez dropped his Pasty on Kun's foot, he flicked it up instinctively and smacked it  Kompany deflecting it past Joe Hart where Balotelli fell over(he was in the penalty area) and ate it. I suppose it takes the Heat Off Vieira so cruelly exposed by City and their PR machine.</body><verb>update</verb><target><id>tag:gnip.disqus.com:2012:thread/672cr9</id><website><id>tag:gnip.disqus.com:2012:forum/gcrd</id></website><link>http://www.telegraph.co.uk/sport/football/teams/manchester-city/9175562/Manchester-City-blow-as-Sergio-Aguero-ruled-out-of-Sunderland-clash-after-picking-up-stupid-injury.html</link><postedTime>2012-03-30T09:39:30+00:00</postedTime><objectType>article</objectType></target><postedTime>2012-03-30T13:33:51+00:00</postedTime><object><id>tag:gnip.disqus.com:2012:comment/mwm0kc</id><link>http://www.telegraph.co.uk/sport/football/teams/manchester-city/9175562/Manchester-City-blow-as-Sergio-Aguero-ruled-out-of-Sunderland-clash-after-picking-up-stupid-injury.html#comment-480743247</link><objectType>comment</objectType></object><actor><id>tag:gnip.disqus.com:2012:account/ez0n7</id><objectType>person</objectType></actor><disqusTypePrev>approved</disqusTypePrev><disqusType>approved</disqusType><platform>disqus</platform><posted_date>2012-03-30</posted_date><followers>0</followers><statuses>0</statuses><region>N.A.</region></marklogic>