<marklogic><id>tag:search.twitter.com,2005:183273346044145664</id><type>P</type><type>P</type><inReplyTo><link>http://twitter.com/With_Effort/statuses/183254050609954816</link></inReplyTo><body>@With_Effort yes but the  is Burnt out. You can still play Wit the cord plugged in or u can just use Batteries</body><verb>post</verb><link>http://twitter.com/its_Leon/statuses/183273346044145664</link><generator><link>http://tapbots.com/tweetbot</link><displayName>Tweetbot for iOS</displayName></generator><postedTime>2012-03-23T19:25:45.000Z</postedTime><provider><link>http://www.twitter.com</link><displayName>Twitter</displayName><objectType>service</objectType></provider><object><summary>@With_Effort yes but the battery is burnt out. You can still play Wit the cord plugged in or u can just use batteries</summary><id>object:search.twitter.com,2005:183273346044145664</id><link>http://twitter.com/its_Leon/statuses/183273346044145664</link><postedTime>2012-03-23T19:25:45.000Z</postedTime><objectType>note</objectType></object><actor><summary>music.twitter.shows.iphone.sports.movies.taurus.</summary><twitterTimeZone>Pacific Time (US &amp; Canada)</twitterTimeZone><friendsCount>77</friendsCount><location><displayName>Not Found</displayName><objectType>place</objectType></location><link>http://www.twitter.com/its_Leon</link><postedTime>2009-05-02T08:48:43.000Z</postedTime><image>http://a0.twimg.com/profile_images/1802621741/image_normal.jpg</image><links><links><rel>me</rel><href/></links></links><listedCount>0</listedCount><id>id:twitter.com:37168521</id><languages><languages>en</languages></languages><utcOffset>-28800</utcOffset><followersCount>66</followersCount><preferredUsername>its_Leon</preferredUsername><displayName>e.Leon</displayName><statusesCount>1130</statusesCount><objectType>person</objectType></actor><twitter_entities><urls/><hashtags/><user_mentions><user_mentions><indices><indices>0</indices><indices>12</indices></indices><name>Cesar S.  :]</name><id_str>457030666</id_str><screen_name>With_Effort</screen_name><id>457030666</id></user_mentions></user_mentions></twitter_entities><objectType>activity</objectType><platform>twitter</platform><posted_date>2012-03-23</posted_date><followers>66</followers><statuses>1130</statuses><region>Pacific</region></marklogic>