<marklogic><id>tag:search.twitter.com,2005:183325273687724034</id><type>P</type><type>P</type><inReplyTo><link>http://twitter.com/Sar_Wah/statuses/183324298050674689</link></inReplyTo><body>@Sar_Wah still much the same as last night. Non stop screaming, Comfort sucking, Hiccups, burping. Nothing seems to calm her down.</body><verb>post</verb><link>http://twitter.com/meganvs/statuses/183325273687724034</link><generator><link>http://twitter.com/#!/download/iphone</link><displayName>Twitter for iPhone</displayName></generator><postedTime>2012-03-23T22:52:05.000Z</postedTime><provider><link>http://www.twitter.com</link><displayName>Twitter</displayName><objectType>service</objectType></provider><object><summary>@Sar_Wah still much the same as last night. Non stop screaming, comfort sucking, hiccups, burping. Nothing seems to calm her down.</summary><id>object:search.twitter.com,2005:183325273687724034</id><link>http://twitter.com/meganvs/statuses/183325273687724034</link><postedTime>2012-03-23T22:52:05.000Z</postedTime><objectType>note</objectType></object><actor><summary>thirty-something mum to one toddler and with a baby due early 2012. Soon to be full time stay at home mum.</summary><twitterTimeZone>Melbourne</twitterTimeZone><friendsCount>145</friendsCount><location><displayName>Melbourne</displayName><objectType>place</objectType></location><link>http://www.twitter.com/meganvs</link><postedTime>2009-03-16T07:16:16.000Z</postedTime><image>http://a0.twimg.com/profile_images/1183003677/jbj3_normal.jpg</image><links><links><rel>me</rel><href/></links></links><listedCount>0</listedCount><id>id:twitter.com:24662562</id><languages><languages>en</languages></languages><utcOffset>36000</utcOffset><followersCount>75</followersCount><preferredUsername>meganvs</preferredUsername><displayName>Megan S</displayName><statusesCount>1421</statusesCount><objectType>person</objectType></actor><twitter_entities><urls/><user_mentions><user_mentions><indices><indices>0</indices><indices>8</indices></indices><name>Sara P</name><screen_name>Sar_Wah</screen_name><id>137697512</id><id_str>137697512</id_str></user_mentions></user_mentions><hashtags/></twitter_entities><objectType>activity</objectType><platform>twitter</platform><posted_date>2012-03-23</posted_date><followers>75</followers><statuses>1421</statuses><region>Melbourne</region></marklogic>