<marklogic><id>tag:search.twitter.com,2005:184728128592162816</id><type>P</type><type>P</type><body>Gotta kick this Colds ass #Nyquil</body><verb>post</verb><link>http://twitter.com/Ninarozay/statuses/184728128592162816</link><generator><link>http://levelupstudio.com/plume</link><displayName>Plume for Android</displayName></generator><postedTime>2012-03-27T19:46:32.000Z</postedTime><provider><link>http://www.twitter.com</link><displayName>Twitter</displayName><objectType>service</objectType></provider><object><summary>Gotta kick this colds ass #nyquil</summary><id>object:search.twitter.com,2005:184728128592162816</id><link>http://twitter.com/Ninarozay/statuses/184728128592162816</link><postedTime>2012-03-27T19:46:32.000Z</postedTime><objectType>note</objectType></object><actor><summary>Crazy♥Sexy♥Cool … That's Me!!! 

(These Are My Thoughts Right Or Wrong Jus What I Was Feeling At The Time..)
 
</summary><twitterTimeZone>Central Time (US &amp; Canada)</twitterTimeZone><friendsCount>740</friendsCount><location><displayName>Live From Pixburgh</displayName><objectType>place</objectType></location><link>http://www.twitter.com/Ninarozay</link><postedTime>2010-12-27T01:19:53.000Z</postedTime><image>http://a0.twimg.com/profile_images/1920940791/R7I7jRyT_normal</image><links><links><rel>me</rel><href/></links></links><listedCount>6</listedCount><id>id:twitter.com:230897629</id><languages><languages>en</languages></languages><utcOffset>-21600</utcOffset><followersCount>836</followersCount><preferredUsername>Ninarozay</preferredUsername><displayName>Nina </displayName><statusesCount>4942</statusesCount><objectType>person</objectType></actor><twitter_entities><urls/><hashtags><hashtags><text>nyquil</text><indices><indices>26</indices><indices>33</indices></indices></hashtags></hashtags><user_mentions/></twitter_entities><objectType>activity</objectType><platform>twitter</platform><posted_date>2012-03-27</posted_date><followers>836</followers><statuses>4942</statuses><region>Central</region></marklogic>