<marklogic><id>tag:search.twitter.com,2005:182786630573240321</id><type>P</type><type>P</type><body>I know The truth is Cold, but please don't Comfort me with a lie if you never want to do it, just say the truth</body><verb>post</verb><link>http://twitter.com/indra_appleseed/statuses/182786630573240321</link><generator><link>http://blackberry.com/twitter</link><displayName>Twitter for BlackBerry®</displayName></generator><postedTime>2012-03-22T11:11:43.000Z</postedTime><provider><link>http://www.twitter.com</link><displayName>Twitter</displayName><objectType>service</objectType></provider><object><summary>I know The truth is cold, but please don't comfort me with a lie if you never want to do it, just say the truth</summary><id>object:search.twitter.com,2005:182786630573240321</id><link>http://twitter.com/indra_appleseed/statuses/182786630573240321</link><postedTime>2012-03-22T11:11:43.000Z</postedTime><objectType>note</objectType></object><actor><summary/><twitterTimeZone>Jakarta</twitterTimeZone><friendsCount>25</friendsCount><location><displayName>Indonesia</displayName><objectType>place</objectType></location><link>http://www.twitter.com/indra_appleseed</link><postedTime>2010-08-23T21:05:54.000Z</postedTime><image>http://a0.twimg.com/profile_images/1878932874/375237_326056607414245_100000297259631_1291740_209197383_n_normal.jpg</image><links><links><rel>me</rel><href>http://black-wanderer.blogspot.com/</href></links></links><listedCount>0</listedCount><id>id:twitter.com:182105230</id><languages><languages>en</languages></languages><utcOffset>25200</utcOffset><followersCount>42</followersCount><preferredUsername>indra_appleseed</preferredUsername><displayName>Indra Gunawan</displayName><statusesCount>2549</statusesCount><objectType>person</objectType></actor><twitter_entities><urls/><user_mentions/><hashtags/></twitter_entities><objectType>activity</objectType><platform>twitter</platform><posted_date>2012-03-22</posted_date><followers>42</followers><statuses>2549</statuses><region>Jakarta</region></marklogic>