<marklogic><id>tag:search.twitter.com,2005:182902339357782017</id><type>P</type><type>P</type><body>just use aluminium foil and Coke to get rid of brown rust Spots on chrome inserts on car - SO martha stewart!</body><verb>post</verb><link>http://twitter.com/harpne/statuses/182902339357782017</link><generator><link>http://ifttt.com</link><displayName>ifttt</displayName></generator><postedTime>2012-03-22T18:51:30.000Z</postedTime><provider><link>http://www.twitter.com</link><displayName>Twitter</displayName><objectType>service</objectType></provider><object><summary>just use aluminium foil and coke to get rid of brown rust spots on chrome inserts on car - SO martha stewart!</summary><id>object:search.twitter.com,2005:182902339357782017</id><link>http://twitter.com/harpne/statuses/182902339357782017</link><postedTime>2012-03-22T18:51:30.000Z</postedTime><objectType>note</objectType></object><actor><summary/><twitterTimeZone>Wellington</twitterTimeZone><friendsCount>442</friendsCount><location><displayName>Thailand</displayName><objectType>place</objectType></location><link>http://www.twitter.com/harpne</link><postedTime>2009-02-08T12:47:17.000Z</postedTime><image>http://a0.twimg.com/profile_images/1234426180/IMG_0065_3_normal.jpg</image><links><links><rel>me</rel><href>http://www.facebook.com/neilharper</href></links></links><listedCount>0</listedCount><id>id:twitter.com:20364487</id><languages><languages>en</languages></languages><utcOffset>43200</utcOffset><followersCount>72</followersCount><preferredUsername>harpne</preferredUsername><displayName>Neil Hrper</displayName><statusesCount>197</statusesCount><objectType>person</objectType></actor><twitter_entities><urls/><user_mentions/><hashtags/></twitter_entities><objectType>activity</objectType><platform>twitter</platform><posted_date>2012-03-22</posted_date><followers>72</followers><statuses>197</statuses><region>Wellington</region></marklogic>