<marklogic><id>tag:search.twitter.com,2005:183525845732823040</id><type>P</type><type>P</type><body>Tylenol Flu and sinus http://t.co/7Hubjh4j</body><verb>post</verb><link>http://twitter.com/tosijalyjenu/statuses/183525845732823040</link><generator><link>http://twitter.com</link><displayName>web</displayName></generator><postedTime>2012-03-24T12:09:06.000Z</postedTime><provider><link>http://www.twitter.com</link><displayName>Twitter</displayName><objectType>service</objectType></provider><object><summary>tylenol flu and sinus http://t.co/7Hubjh4j</summary><id>object:search.twitter.com,2005:183525845732823040</id><link>http://twitter.com/tosijalyjenu/statuses/183525845732823040</link><postedTime>2012-03-24T12:09:06.000Z</postedTime><objectType>note</objectType></object><actor><summary>My favorite artists - System of a Down and Frank Zappa/The Mothers of Invention. About me:forgiven, full and sonorous.&#13;</summary><twitterTimeZone/><friendsCount>6</friendsCount><location><displayName>IA&#13;</displayName><objectType>place</objectType></location><link>http://www.twitter.com/tosijalyjenu</link><postedTime>2012-03-09T12:35:29.000Z</postedTime><image>http://a0.twimg.com/profile_images/1884412777/79_normal.gif</image><links><links><rel>me</rel><href/></links></links><listedCount>0</listedCount><id>id:twitter.com:519448665</id><languages><languages>en</languages></languages><utcOffset/><followersCount>5</followersCount><preferredUsername>tosijalyjenu</preferredUsername><displayName>paleo</displayName><statusesCount>15</statusesCount><objectType>person</objectType></actor><twitter_entities><urls><urls><expanded_url>http://tylenol-flu-and-sinus.cheapillsshop.com</expanded_url><indices><indices>22</indices><indices>42</indices></indices><display_url>…lenol-flu-and-sinus.cheapillsshop.com</display_url><url>http://t.co/7Hubjh4j</url></urls></urls><user_mentions/><hashtags/></twitter_entities><objectType>activity</objectType><platform>twitter</platform><posted_date>2012-03-24</posted_date><followers>5</followers><statuses>15</statuses><region>N.A.</region></marklogic>