<marklogic><id>tag:search.twitter.com,2005:184758313232244736</id><type>P</type><type>P</type><body>Fanta fruit twist hit the Spot.</body><verb>post</verb><link>http://twitter.com/JordanCoombes/statuses/184758313232244736</link><generator><link>http://twitter.com/#!/download/ipad</link><displayName>Twitter for iPad</displayName></generator><postedTime>2012-03-27T21:46:29.000Z</postedTime><provider><link>http://www.twitter.com</link><displayName>Twitter</displayName><objectType>service</objectType></provider><object><summary>Fanta fruit twist hit the spot.</summary><id>object:search.twitter.com,2005:184758313232244736</id><link>http://twitter.com/JordanCoombes/statuses/184758313232244736</link><postedTime>2012-03-27T21:46:29.000Z</postedTime><objectType>note</objectType></object><actor><summary>Fortune favours the bold.</summary><twitterTimeZone>London</twitterTimeZone><friendsCount>503</friendsCount><location><displayName>Lowestoft, Suffolk.</displayName><objectType>place</objectType></location><link>http://www.twitter.com/JordanCoombes</link><postedTime>2009-06-18T13:07:54.000Z</postedTime><image>http://a0.twimg.com/profile_images/1972449348/image_normal.jpg</image><links><links><rel>me</rel><href/></links></links><listedCount>0</listedCount><id>id:twitter.com:48343211</id><languages><languages>en</languages></languages><utcOffset>0</utcOffset><followersCount>309</followersCount><preferredUsername>JordanCoombes</preferredUsername><displayName>Jordan Coombes</displayName><statusesCount>6837</statusesCount><objectType>person</objectType></actor><twitter_entities><hashtags/><user_mentions/><urls/></twitter_entities><objectType>activity</objectType><platform>twitter</platform><posted_date>2012-03-27</posted_date><followers>309</followers><statuses>6837</statuses><region>London</region></marklogic>