<marklogic><id>tag:search.twitter.com,2005:184937863710900225</id><type>P</type><type>P</type><body>My top 3 mentioners: @Joe_Scott_Sykes (79),  @Burn__inthehell (71),  @iisalinke (65), see yours at http://t.co/LvU7KGKc via #TwitMentionable</body><verb>post</verb><link>http://twitter.com/CamiiHeree/statuses/184937863710900225</link><generator><link>http://94.76.233.68/~twitment/</link><displayName>TwitMentionable Temp</displayName></generator><postedTime>2012-03-28T09:39:57.000Z</postedTime><provider><link>http://www.twitter.com</link><displayName>Twitter</displayName><objectType>service</objectType></provider><object><summary>My top 3 mentioners: @Joe_Scott_Sykes (79),  @Burn__inthehell (71),  @iisalinke (65), see yours at http://t.co/LvU7KGKc via #TwitMentionable</summary><id>object:search.twitter.com,2005:184937863710900225</id><link>http://twitter.com/CamiiHeree/statuses/184937863710900225</link><postedTime>2012-03-28T09:39:57.000Z</postedTime><objectType>note</objectType></object><actor><summary>I'm your ch ch ch ch ch cherry bomb.*o* 'nhaa' \m/ CamiiHeree :3 Escape The Fate \Diamantes e Cerejas/ Camila Prohmann | Contact : Camilapg_@hotmail.com . </summary><twitterTimeZone>Greenland</twitterTimeZone><friendsCount>291</friendsCount><location><displayName>CWB</displayName><objectType>place</objectType></location><link>http://www.twitter.com/CamiiHeree</link><postedTime>2009-11-13T23:30:38.000Z</postedTime><image>http://a0.twimg.com/profile_images/1870235655/421938_313834242007440_100001426000028_905650_1966442937_n_normal.jpg</image><links><links><rel>me</rel><href>http://poisonstorm.tumblr.com/</href></links></links><listedCount>51</listedCount><id>id:twitter.com:89821447</id><languages><languages>en</languages></languages><utcOffset>-10800</utcOffset><followersCount>662</followersCount><preferredUsername>CamiiHeree</preferredUsername><displayName>Camila Prohmann :3</displayName><statusesCount>26129</statusesCount><objectType>person</objectType></actor><twitter_entities><hashtags><hashtags><text>TwitMentionable</text><indices><indices>124</indices><indices>140</indices></indices></hashtags></hashtags><user_mentions><user_mentions><indices><indices>21</indices><indices>37</indices></indices><name>Menino do BFMV *-*</name><id_str>371245637</id_str><id>371245637</id><screen_name>Joe_Scott_Sykes</screen_name></user_mentions><user_mentions><indices><indices>45</indices><indices>61</indices></indices><name>Bruno C. Ribeiro</name><id_str>522394592</id_str><id>522394592</id><screen_name>Burn__inthehell</screen_name></user_mentions><user_mentions><indices><indices>69</indices><indices>79</indices></indices><name>Isabella Beluchi ☮</name><id_str>229969933</id_str><id>229969933</id><screen_name>iisalinke</screen_name></user_mentions></user_mentions><urls><urls><indices><indices>99</indices><indices>119</indices></indices><expanded_url>http://www.twitmentionable.tk</expanded_url><display_url>twitmentionable.tk</display_url><url>http://t.co/LvU7KGKc</url></urls></urls></twitter_entities><objectType>activity</objectType><platform>twitter</platform><posted_date>2012-03-28</posted_date><followers>662</followers><statuses>26129</statuses><region>Greenland</region></marklogic>