<marklogic><id>tag:search.twitter.com,2005:183792306992852992</id><type>P</type><type>P</type><body>Taming frizzy hair, healing Dry skin: If the curl is natural, read on. If it's a perm, stop it. Dear Scott: I am... http://t.co/Pd1NfrWr</body><verb>post</verb><link>http://twitter.com/BeOrganicLife/statuses/183792306992852992</link><generator><link>http://twitterfeed.com</link><displayName>twitterfeed</displayName></generator><postedTime>2012-03-25T05:47:55.000Z</postedTime><provider><link>http://www.twitter.com</link><displayName>Twitter</displayName><objectType>service</objectType></provider><object><summary>Taming frizzy hair, healing dry skin: If the curl is natural, read on. If it's a perm, stop it. Dear Scott: I am... http://t.co/Pd1NfrWr</summary><id>object:search.twitter.com,2005:183792306992852992</id><link>http://twitter.com/BeOrganicLife/statuses/183792306992852992</link><postedTime>2012-03-25T05:47:55.000Z</postedTime><objectType>note</objectType></object><actor><summary>I advocate for healthy living, including natural health care, natural skin care, organic food, green lifestyle, and natural healing.</summary><twitterTimeZone>Mountain Time (US &amp; Canada)</twitterTimeZone><friendsCount>3819</friendsCount><link>http://www.twitter.com/BeOrganicLife</link><postedTime>2010-01-09T08:52:24.000Z</postedTime><image>http://a0.twimg.com/profile_images/626029189/leaf_normal.jpg</image><links><links><rel>me</rel><href>http://www.BeOrganicLife.blogspot.com</href></links></links><listedCount>93</listedCount><id>id:twitter.com:103225253</id><languages><languages>en</languages></languages><utcOffset>-25200</utcOffset><followersCount>4397</followersCount><preferredUsername>BeOrganicLife</preferredUsername><displayName>Well Being</displayName><statusesCount>23164</statusesCount><objectType>person</objectType></actor><twitter_entities><urls><urls><expanded_url>http://bit.ly/GZ2ulf</expanded_url><indices><indices>116</indices><indices>136</indices></indices><display_url>bit.ly/GZ2ulf</display_url><url>http://t.co/Pd1NfrWr</url></urls></urls><user_mentions/><hashtags/></twitter_entities><objectType>activity</objectType><platform>twitter</platform><posted_date>2012-03-25</posted_date><followers>4397</followers><statuses>23164</statuses><region>Mountain</region></marklogic>