<marklogic><id>tag:search.twitter.com,2005:184688799069122560</id><type>P</type><type>P</type><body> and Tylenol Cold at the same time http://t.co/T2MYYHZS</body><verb>post</verb><link>http://twitter.com/modadabolox/statuses/184688799069122560</link><generator><link>http://twitter.com</link><displayName>web</displayName></generator><postedTime>2012-03-27T17:10:15.000Z</postedTime><provider><link>http://www.twitter.com</link><displayName>Twitter</displayName><objectType>service</objectType></provider><object><summary>claritin and tylenol cold at the same time http://t.co/T2MYYHZS</summary><id>object:search.twitter.com,2005:184688799069122560</id><link>http://twitter.com/modadabolox/statuses/184688799069122560</link><postedTime>2012-03-27T17:10:15.000Z</postedTime><objectType>note</objectType></object><actor><summary>I'm blustered, 295. Netted and restive. Also debilitating and futile. Listen to Os Mutantes.&#13;</summary><twitterTimeZone/><friendsCount>43</friendsCount><location><displayName>GB&#13;</displayName><objectType>place</objectType></location><link>http://www.twitter.com/modadabolox</link><postedTime>2012-02-05T03:24:24.000Z</postedTime><image>http://a0.twimg.com/profile_images/1806604024/1793_normal.gif</image><links><links><rel>me</rel><href/></links></links><listedCount>0</listedCount><id>id:twitter.com:483516482</id><languages><languages>es</languages></languages><utcOffset/><followersCount>9</followersCount><preferredUsername>modadabolox</preferredUsername><displayName>stoutamire</displayName><statusesCount>146</statusesCount><objectType>person</objectType></actor><twitter_entities><urls><urls><indices><indices>43</indices><indices>63</indices></indices><display_url>…ld-at-the-same-time.cheapillsshop.com</display_url><url>http://t.co/T2MYYHZS</url><expanded_url>http://claritin-and-tylenol-cold-at-the-same-time.cheapillsshop.com</expanded_url></urls></urls><hashtags/><user_mentions/></twitter_entities><objectType>activity</objectType><platform>twitter</platform><posted_date>2012-03-27</posted_date><followers>9</followers><statuses>146</statuses><region>N.A.</region></marklogic>